{
  "_fv": 33,
  "_type": "recipe",
  "definition": {
    "recipeType": "Crafting",
    "xpReward": 0.0,
    "cookingTime": 200,
    "recipeRetstackSize": 1,
    "group": "",
    "recipeShapeless": false,
    "recipeSlots": [
      {
        "value": "CUSTOM:K7A2WoodPlanks"
      },
      {
        "value": "CUSTOM:K7A2WoodPlanks"
      },
      {
        "value": ""
      },
      {
        "value": "CUSTOM:K7A2WoodPlanks"
      },
      {
        "value": "CUSTOM:K7A2WoodPlanks"
      },
      {
        "value": ""
      },
      {
        "value": ""
      },
      {
        "value": ""
      },
      {
        "value": ""
      }
    ],
    "recipeReturnStack": {
      "value": "Blocks.CRAFTING_TABLE"
    },
    "name": "k_7_a_2_crafting_table",
    "namespace": "mod"
  }
}