{"stats":{"minecraft:killed":{"minecraft:pig":1},"minecraft:picked_up":{"minecraft:porkchop":2,"minecraft:sand":1,"minecraft:glowstone_dust":2},"minecraft:used":{"minecraft:glowstone":15,"k7a2:aether":13,"minecraft:porkchop":2},"minecraft:custom":{"minecraft:time_since_rest":2984,"minecraft:play_one_minute":2984,"minecraft:crouch_one_cm":144,"minecraft:sprint_one_cm":6792,"minecraft:damage_taken":60,"minecraft:walk_one_cm":7949,"minecraft:sneak_time":53,"minecraft:mob_kills":1,"minecraft:jump":99,"minecraft:damage_dealt":205,"minecraft:leave_game":1,"minecraft:time_since_death":2984,"minecraft:fall_one_cm":2967,"minecraft:fly_one_cm":9098},"minecraft:crafted":{"k7a2:aether":1},"minecraft:mined":{"minecraft:grass":1,"minecraft:glowstone":1,"minecraft:sand":1}},"DataVersion":2586}